{"accuracy": 0.07065352814588288, "precision": 0.004991921039461065, "recall": 0.07065352814588288, "f1_score": 0.009324998065631716, "confusion_matrix": [[0, 3103, 0, 0], [0, 3119, 0, 0], [0, 23772, 0, 0], [0, 14151, 0, 0]], "classification_report": "              precision    recall  f1-score   support\n\n    hypernym       0.00      0.00      0.00      3103\n     hyponym       0.07      1.00      0.13      3119\n        none       0.00      0.00      0.00     23772\n    synonymy       0.00      0.00      0.00     14151\n\n    accuracy                           0.07     44145\n   macro avg       0.02      0.25      0.03     44145\nweighted avg       0.00      0.07      0.01     44145\n", "timestamp": 1726588292, "checkpoint_dir_name": "checkpoint_000000", "should_checkpoint": true, "done": false, "training_iteration": 1, "trial_id": "ec25e_00116", "date": "2024-09-17_18-51-32", "time_this_iter_s": 952.9513006210327, "time_total_s": 952.9513006210327, "pid": 32240, "hostname": "Davidovic", "node_ip": "127.0.0.1", "config": {"lr": 3.355940077920745e-09, "num_epochs": 123, "batch_size": 64, "hidden_sizes": [512, 256, 128, 64], "activation": "relu", "optimizer": "SGD", "dropout_rate": 0.0, "postive_percentage": 0.5}, "time_since_restore": 952.9513006210327, "iterations_since_restore": 1}
